{"current": [{"fvTenant": {"attributes": {"dn": "uni/tn-ZZ-AUTOMATION-TESTE001", "status": "", "ownerKey": "", "uid": "12748", "descr": "Tenant teste Projeto Automacao", "extMngdBy": "", "name": "ZZ-AUTOMATION-TESTE001", "lcOwn": "local", "monPolDn": "uni/tn-common/monepg-default", "nameAlias": "", "ownerTag": "", "modTs": "2020-05-18T23:42:29.865-03:00", "annotation": "", "childAction": ""}, "children": [{"fvAp": {"attributes": {"status": "", "lcOwn": "local", "ownerKey": "", "uid": "13673", "prio": "unspecified", "extMngdBy": "", "descr": "AP from Tenant 001 Proj Automacao", "name": "AP-TESTE003", "monPolDn": "uni/tn-common/monepg-default", "nameAlias": "", "ownerTag": "", "rn": "ap-AP-TESTE003", "modTs": "2020-05-27T12:25:30.460-03:00", "annotation": "", "childAction": ""}}}, {"fvAp": {"attributes": {"status": "", "lcOwn": "local", "ownerKey": "", "uid": "13673", "prio": "unspecified", "extMngdBy": "", "descr": "AP from Tenant 001 Proj Automacao", "name": "AP-TESTE002", "monPolDn": "uni/tn-common/monepg-default", "nameAlias": "", "ownerTag": "", "rn": "ap-AP-TESTE002", "modTs": "2020-05-27T12:24:59.922-03:00", "annotation": "", "childAction": ""}}}, {"fvAp": {"attributes": {"status": "", "lcOwn": "local", "ownerKey": "", "uid": "13673", "prio": "unspecified", "extMngdBy": "", "descr": "AP from Tenant 001 Proj Automacao", "name": "AP-TESTE", "monPolDn": "uni/tn-common/monepg-default", "nameAlias": "", "ownerTag": "", "rn": "ap-AP-TESTE", "modTs": "2020-05-27T12:43:37.927-03:00", "annotation": "", "childAction": ""}, "children": [{"fvAEPg": {"attributes": {"uid": "13673", "prio": "unspecified", "extMngdBy": "", "isAttrBasedEPg": "no", "matchT": "AtleastOne", "descr": "", "prefGrMemb": "include", "monPolDn": "uni/tn-common/monepg-default", "modTs": "2020-05-27T14:07:14.573-03:00", "scope": "2850819", "rn": "epg-EPG-TESTE", "pcEnfPref": "unenforced", "status": "", "nameAlias": "", "fwdCtrl": "", "configIssues": "", "configSt": "applied", "txId": "6341068275364586339", "triggerSt": "triggerable", "isSharedSrvMsiteEPg": "no", "annotation": "", "childAction": "", "lcOwn": "local", "name": "EPG-TESTE", "pcTag": "49157", "exceptionTag": "", "floodOnEncap": "disabled"}, "children": [{"fvRsBd": {"attributes": {"status": "", "lcOwn": "local", "tRn": "BD-BD_TESTE", "uid": "0", "rType": "mo", "stateQual": "none", "state": "formed", "tCl": "fvBD", "forceResolve": "yes", "tContextDn": "", "modTs": "2020-05-27T14:07:14.523-03:00", "tnFvBDName": "BD_TESTE", "extMngdBy": "", "tType": "name", "rn": "rsbd", "tDn": "uni/tn-ZZ-AUTOMATION-TESTE001/BD-BD_TESTE", "annotation": "", "monPolDn": "uni/tn-common/monepg-default", "childAction": ""}, "children": [{"fvSubnetBDDefCont": {"attributes": {"lcOwn": "local", "status": "", "name": "", "nameAlias": "", "bddefDn": "uni/bd-[uni/tn-ZZ-AUTOMATION-TESTE001/BD-BD_TESTE]-isSvc-no", "monPolDn": "uni/tn-common/monepg-default", "modTs": "2020-05-27T14:07:14.523-03:00", "rn": "subnetBddefDn-[uni/bd-[uni/tn-ZZ-AUTOMATION-TESTE001/BD-BD_TESTE]-isSvc-no]", "childAction": "deleteNonPresent"}}}]}}]}}]}}, {"fvAp": {"attributes": {"status": "", "lcOwn": "local", "ownerKey": "", "uid": "13673", "prio": "unspecified", "extMngdBy": "", "descr": "AP from Tenant 001 Proj Automacao", "name": "AP-TESTE001", "monPolDn": "uni/tn-common/monepg-default", "nameAlias": "", "ownerTag": "", "rn": "ap-AP-TESTE001", "modTs": "2020-05-19T00:08:01.792-03:00", "annotation": "", "childAction": ""}, "children": [{"fvAEPg": {"attributes": {"uid": "13673", "prio": "unspecified", "extMngdBy": "", "isAttrBasedEPg": "no", "matchT": "AtleastOne", "descr": "", "prefGrMemb": "include", "monPolDn": "uni/tn-common/monepg-default", "modTs": "2020-05-27T14:08:05.458-03:00", "scope": "2850819", "rn": "epg-EPG-TESTE-001", "pcEnfPref": "unenforced", "status": "", "nameAlias": "", "fwdCtrl": "", "configIssues": "", "configSt": "applied", "txId": "6341068275364586399", "triggerSt": "triggerable", "isSharedSrvMsiteEPg": "no", "annotation": "", "childAction": "", "lcOwn": "local", "name": "EPG-TESTE-001", "pcTag": "16387", "exceptionTag": "", "floodOnEncap": "disabled"}, "children": [{"fvRsBd": {"attributes": {"status": "", "lcOwn": "local", "tRn": "BD-BD_TESTE-001", "uid": "0", "rType": "mo", "stateQual": "none", "state": "formed", "tCl": "fvBD", "forceResolve": "yes", "tContextDn": "", "modTs": "2020-05-27T14:08:05.377-03:00", "tnFvBDName": "BD_TESTE-001", "extMngdBy": "", "tType": "name", "rn": "rsbd", "tDn": "uni/tn-ZZ-AUTOMATION-TESTE001/BD-BD_TESTE-001", "annotation": "", "monPolDn": "uni/tn-common/monepg-default", "childAction": ""}, "children": [{"fvSubnetBDDefCont": {"attributes": {"lcOwn": "local", "status": "", "name": "", "nameAlias": "", "bddefDn": "uni/bd-[uni/tn-ZZ-AUTOMATION-TESTE001/BD-BD_TESTE-001]-isSvc-no", "monPolDn": "uni/tn-common/monepg-default", "modTs": "2020-05-27T14:08:05.377-03:00", "rn": "subnetBddefDn-[uni/bd-[uni/tn-ZZ-AUTOMATION-TESTE001/BD-BD_TESTE-001]-isSvc-no]", "childAction": "deleteNonPresent"}}}]}}]}}]}}]}}], "failed": false, "changed": false}